devtools/autorelease_check.py
devtools/setup_cfg_reqs.py
devtools/ci/push-docs-to-s3.py
docs/conf.py
docs/premake.py
docs/copyfiles/copyfiles.py
docs/sphinxext/notebook_sphinxext.py
docs/sphinxext/pandoc_sphinxext.py
examples/prep_example_data.py
examples/alanine_dipeptide_mstis/alatools.py
examples/resources/toy_plot_helpers.py
openpathsampling/.gitignore
openpathsampling/README.md
openpathsampling/__init__.py
openpathsampling/_installed_version.py
openpathsampling/bias_function.py
openpathsampling/collectivevariable.py
openpathsampling/deprecations.py
openpathsampling/ensemble.py
openpathsampling/integration_tools.py
openpathsampling/logging.conf
openpathsampling/movechange.py
openpathsampling/ops_logging.py
openpathsampling/pathmover.py
openpathsampling/pathmover_inout.py
openpathsampling/progress.py
openpathsampling/range_logic.py
openpathsampling/rng.py
openpathsampling/sample.py
openpathsampling/shooting.py
openpathsampling/snapshot_modifier.py
openpathsampling/step_visualizer_2D.py
openpathsampling/tools.py
openpathsampling/treelogic.py
openpathsampling/version.py
openpathsampling/visualize.py
openpathsampling/volume.py
openpathsampling/analysis/.gitignore
openpathsampling/analysis/__init__.py
openpathsampling/analysis/channel_analysis.py
openpathsampling/analysis/ensemble_representation.py
openpathsampling/analysis/path_histogram.py
openpathsampling/analysis/reactive_flux_analysis.py
openpathsampling/analysis/replica_network.py
openpathsampling/analysis/shooting_point_analysis.py
openpathsampling/analysis/sshooting_analysis.py
openpathsampling/analysis/tools.py
openpathsampling/analysis/trajectory_transition_analysis.py
openpathsampling/analysis/tis/__init__.py
openpathsampling/analysis/tis/core.py
openpathsampling/analysis/tis/crossing_probability.py
openpathsampling/analysis/tis/flux.py
openpathsampling/analysis/tis/misc.py
openpathsampling/analysis/tis/standard_analysis.py
openpathsampling/beta/__init__.py
openpathsampling/beta/hooks.py
openpathsampling-1.7.0.dist-info/LICENSE
openpathsampling-1.7.0.dist-info/METADATA
openpathsampling-1.7.0.dist-info/WHEEL
openpathsampling-1.7.0.dist-info/top_level.txt
openpathsampling-1.7.0.dist-info/RECORD
